vtag/__init__.py
vtag/__main__.py
vtag/core/__init__.py
vtag/core/clustering.py
vtag/core/contour.py
vtag/core/motion.py
vtag/core/tracking.py
vtag/core/utils.py
vtag/core/visualization.py
vtag/core/vtag.py
vtag/core/vtstream.py
vtag/gui/colors.py
vtag/gui/utils.py
vtag/gui/vtframe.py
vtag/gui/vtgui.py
vtag/gui/vtplayback.py
python_vtag-0.9.2.dist-info/LICENSE
python_vtag-0.9.2.dist-info/METADATA
python_vtag-0.9.2.dist-info/WHEEL
python_vtag-0.9.2.dist-info/top_level.txt
python_vtag-0.9.2.dist-info/RECORD
