Metadata-Version: 2.1
Name: python-vtag
Version: 0.9.2
Summary: Semi-Supervised Top-View Animal Tracking
Home-page: https://github.com/vt-ads/vtag
Author: James Chen
Author-email: niche@vt.edu
License: GPLv3
Platform: UNKNOWN
Classifier: Programming Language :: Python :: 3.8
Classifier: License :: OSI Approved :: GNU General Public License v3 (GPLv3)
Classifier: Operating System :: MacOS :: MacOS X
Classifier: Operating System :: Microsoft :: Windows :: Windows 10
Requires-Python: >=3.8
License-File: LICENSE
Requires-Dist: numpy
Requires-Dist: pandas (>=0.19.2)
Requires-Dist: sklearn
Requires-Dist: scipy
Requires-Dist: matplotlib
Requires-Dist: opencv-python
Requires-Dist: opencv-contrib-pythonPyQt6
Requires-Dist: qdarkstyle
